{"obj_edit_time":"1770018393","blocks":[{"block_id":"STqId0Ob7oG8fdx5Hiqji7YYple","block_type":1,"children":["doxjpdVEfGdT8LmI4xFUAFrVtof","doxjpNtvIheAE3OPeQidKRE4J2b","AMn1dXD4Co54PuxpwTBjpZOopxc"],"page":{"elements":[{"text_run":{"content":"Whale Console","text_element_style":{"bold":false,"inline_code":false,"italic":false,"strikethrough":false,"underline":false}}}],"style":{"align":1}},"parent_id":""},{"block_id":"doxjpdVEfGdT8LmI4xFUAFrVtof","block_type":14,"code":{"elements":[{"text_run":{"content":"slug: ","text_element_style":{"bold":false,"inline_code":false,"italic":false,"strikethrough":false,"underline":false}}},{"text_run":{"content":"G3LGw8hlOieaJXkLGuxcQVTtndf","text_element_style":{"bold":false,"inline_code":false,"italic":false,"strikethrough":false,"underline":false}}},{"text_run":{"content":"\n","text_element_style":{"bold":false,"inline_code":false,"italic":false,"strikethrough":false,"underline":false}}}],"style":{"language":67,"wrap":false}},"parent_id":"STqId0Ob7oG8fdx5Hiqji7YYple"},{"block_id":"doxjpNtvIheAE3OPeQidKRE4J2b","block_type":2,"parent_id":"STqId0Ob7oG8fdx5Hiqji7YYple","text":{"elements":[{"text_run":{"content":"","text_element_style":{"bold":false,"inline_code":false,"italic":false,"strikethrough":false,"underline":false}}}],"style":{"align":1,"folded":false}}},{"block_id":"AMn1dXD4Co54PuxpwTBjpZOopxc","block_type":2,"parent_id":"STqId0Ob7oG8fdx5Hiqji7YYple","text":{"elements":[{"text_run":{"content":"","text_element_style":{"bold":false,"inline_code":false,"italic":false,"strikethrough":false,"underline":false}}}],"style":{"align":1,"folded":false}}}]}