{"obj_edit_time":"1769007994","blocks":[{"block_id":"SWLGd8QCLopsDQx7Qlej7qJ8pkg","block_type":1,"children":["doxjp30k6qY6GpZJ98vWhjV0BCd","doxjpGsDoZWne52havU6Hhl5ZXd"],"page":{"elements":[{"text_run":{"content":"PageHub","text_element_style":{"bold":false,"inline_code":false,"italic":false,"strikethrough":false,"underline":false}}}],"style":{"align":1}},"parent_id":""},{"block_id":"doxjp30k6qY6GpZJ98vWhjV0BCd","block_type":14,"code":{"elements":[{"text_run":{"content":"slug: HIYMwktOui1w6skOympcYuAKnLc\ntitle: PageHub\n","text_element_style":{"bold":false,"inline_code":false,"italic":false,"strikethrough":false,"underline":false}}},{"text_run":{"content":"sidebar_position: 3","text_element_style":{"bold":false,"inline_code":false,"italic":false,"strikethrough":false,"underline":false}}}],"style":{"language":67,"wrap":false}},"parent_id":"SWLGd8QCLopsDQx7Qlej7qJ8pkg"},{"block_id":"doxjpGsDoZWne52havU6Hhl5ZXd","block_type":3,"heading1":{"elements":[{"text_run":{"content":"PageHub","text_element_style":{"bold":false,"inline_code":false,"italic":false,"strikethrough":false,"underline":false}}}],"style":{"align":1,"folded":false}},"parent_id":"SWLGd8QCLopsDQx7Qlej7qJ8pkg"}]}